weaviate_client/__init__.py
weaviate_client/client.py
weaviate_client/errors.py
weaviate_client/py.typed
weaviate_client/types.py
weaviate_client/api/__init__.py
weaviate_client/api/authz/__init__.py
weaviate_client/api/authz/add_permissions.py
weaviate_client/api/authz/assign_role_to_group.py
weaviate_client/api/authz/assign_role_to_user.py
weaviate_client/api/authz/create_role.py
weaviate_client/api/authz/delete_role.py
weaviate_client/api/authz/get_role.py
weaviate_client/api/authz/get_roles.py
weaviate_client/api/authz/get_roles_for_user.py
weaviate_client/api/authz/get_roles_for_user_deprecated.py
weaviate_client/api/authz/get_users_for_role.py
weaviate_client/api/authz/get_users_for_role_deprecated.py
weaviate_client/api/authz/has_permission.py
weaviate_client/api/authz/remove_permissions.py
weaviate_client/api/authz/revoke_role_from_group.py
weaviate_client/api/authz/revoke_role_from_user.py
weaviate_client/api/backups/__init__.py
weaviate_client/api/backups/backups_cancel.py
weaviate_client/api/backups/backups_create.py
weaviate_client/api/backups/backups_create_status.py
weaviate_client/api/backups/backups_list.py
weaviate_client/api/backups/backups_restore.py
weaviate_client/api/backups/backups_restore_status.py
weaviate_client/api/batch/__init__.py
weaviate_client/api/batch/batch_objects_create.py
weaviate_client/api/batch/batch_objects_delete.py
weaviate_client/api/batch/batch_references_create.py
weaviate_client/api/classifications/__init__.py
weaviate_client/api/classifications/classifications_get.py
weaviate_client/api/classifications/classifications_post.py
weaviate_client/api/cluster/__init__.py
weaviate_client/api/cluster/cluster_get_statistics.py
weaviate_client/api/distributed_tasks/__init__.py
weaviate_client/api/distributed_tasks/distributed_tasks_get.py
weaviate_client/api/graphql/__init__.py
weaviate_client/api/graphql/graphql_batch.py
weaviate_client/api/graphql/graphql_post.py
weaviate_client/api/meta/__init__.py
ians_weaaviate_client-0.0.1.dist-info/METADATA
ians_weaaviate_client-0.0.1.dist-info/WHEEL
ians_weaaviate_client-0.0.1.dist-info/RECORD
