Metadata-Version: 2.4
Name: ians-weaaviate-client
Version: 0.0.1
Summary: A client library for accessing Weaviate generated from openapi spec
Requires-Python: ~=3.9
Requires-Dist: attrs>=22.2.0
Requires-Dist: httpx<0.29.0,>=0.23.0
Requires-Dist: python-dateutil<3,>=2.8.0
